README.rst
lanfit_resp.py
setup.py
lanfit_resp.egg-info/PKG-INFO
lanfit_resp.egg-info/SOURCES.txt
lanfit_resp.egg-info/dependency_links.txt
lanfit_resp.egg-info/requires.txt
lanfit_resp.egg-info/top_level.txt