Metadata-Version: 1.1
Name: lanfit-resp
Version: 0.1.2
Summary: requests to flask response with Link header.
Home-page: UNKNOWN
Author: ll1l11
Author-email: ll1l11@qq.com
License: MIT
Platform: UNKNOWN
Classifier: Programming Language :: Python :: 3
